perceptronpy/__init__.py
perceptronpy/perceptron.py
oneNeuron_pypi_BenRoshan100-0.0.2.dist-info/LICENSE
oneNeuron_pypi_BenRoshan100-0.0.2.dist-info/METADATA
oneNeuron_pypi_BenRoshan100-0.0.2.dist-info/WHEEL
oneNeuron_pypi_BenRoshan100-0.0.2.dist-info/top_level.txt
oneNeuron_pypi_BenRoshan100-0.0.2.dist-info/RECORD
