Metadata-Version: 2.1
Name: oneNeuron-pypi-BenRoshan100
Version: 0.0.2
Summary: its an implimentation of Perceptron
Home-page: https://github.com/BenRoshan100/oneNeuron_pypi
Author: BenRoshan100
Author-email: benroshan100@gmail.com
Project-URL: Bug Tracker, https://github.com/BenRoshan100/oneNeuron_pypi/issues
Classifier: Programming Language :: Python :: 3
Classifier: License :: OSI Approved :: MIT License
Classifier: Operating System :: OS Independent
Requires-Python: >=3.7
License-File: LICENSE
Requires-Dist: numpy
Requires-Dist: tqdm
